{
  "id": 22181,
  "title": "1959년 Siegal 사건",
  "category": "crime",
  "era": "contemporary",
  "date": "1959-03-11",
  "location": "New York, NY, USA",
  "summary": "미국 New York, NY 법원 판결 사건. 사건명: Siegal. 판결일: 1959-03-11. 법원: Appellate Division of the Supreme Court of the State of New York.",
  "description": "## 사건 정보\n\n**사건명**: In the Matter of Herbert S. Siegal, on Behalf of Anthony Vellucci, against Warden of Attica State Prison\n**판결일**: 1959-03-11\n**법원**: Appellate Division of the Supreme Court of the State of New York\n**관할**: New York, NY\n\n## 인용\n\n- 8 A.D.2d 583\n\n## 판결문 요약\n\n\nOrder affirmed, without costs of this appeal to either party. All concur. (Appeal from an order of Wyoming County Court dismissing a writ of habeas corpus and remanding the prisoner to the custody of the Warden of Attica Prison.) Present — McCurn, P. J., Kimball, Bastow, Goldman and Halpern, JJ.\n...",
  "timeline": [],
  "theories": [],
  "tags": [
    "범죄",
    "미국",
    "법원판결",
    "판례"
  ],
  "sources": [
    {
      "name": "Harvard Law - Case Law Access Project",
      "url": "https://case.law/search?q=siegal-v-warden-of-attica-state-prison"
    }
  ],
  "relatedIncidents": [
    22056,
    22060,
    22061,
    22064,
    22065
  ],
  "images": [],
  "casualties": null,
  "coordinates": null,
  "status": "resolved"
}