{
  "id": 25302,
  "title": "M6.6 지진 - Volcano Islands, Japan region",
  "category": "disaster",
  "era": "contemporary",
  "date": "1939-05-17",
  "location": "Volcano Islands, Japan region",
  "summary": "1939-05-17에 Volcano Islands, Japan region에서 발생한 규모 6.6의 강진 (Strong). ",
  "description": "## 지진 정보\n\n**규모**: M6.6 (강진 (Strong))\n**발생 시각**: 1939-05-17 18:30:38 UTC\n**위치**: Volcano Islands, Japan region\n**깊이**: 35.0 km\n**좌표**: 23.1010°N, 143.4180°E\n\n",
  "timeline": [],
  "theories": [],
  "tags": [
    "자연재해",
    "지진",
    "재난"
  ],
  "sources": [
    {
      "name": "USGS",
      "url": "https://earthquake.usgs.gov/earthquakes/eventpage/iscgem901977"
    }
  ],
  "relatedIncidents": [
    25234,
    25235,
    25236,
    25237,
    25238
  ],
  "images": [],
  "casualties": null,
  "coordinates": {
    "lat": 23.101,
    "lng": 143.418
  },
  "status": "resolved",
  "magnitude": 6.64,
  "depth": 35
}