{
  "id": 27588,
  "title": "M6.0 지진 - 62 km SSW of Abepura, Indonesia",
  "category": "disaster",
  "era": "contemporary",
  "date": "1925-06-11",
  "location": "62 km SSW of Abepura, Indonesia",
  "summary": "1925-06-11에 62 km SSW of Abepura, Indonesia에서 발생한 규모 6.0의 강진 (Strong). ",
  "description": "## 지진 정보\n\n**규모**: M6.0 (강진 (Strong))\n**발생 시각**: 1925-06-11 15:56:52 UTC\n**위치**: 62 km SSW of Abepura, Indonesia\n**깊이**: 35.0 km\n**좌표**: -3.0820°N, 140.3440°E\n\n",
  "timeline": [],
  "theories": [],
  "tags": [
    "자연재해",
    "지진",
    "재난"
  ],
  "sources": [
    {
      "name": "USGS",
      "url": "https://earthquake.usgs.gov/earthquakes/eventpage/iscgem910535"
    }
  ],
  "relatedIncidents": [
    27510,
    27511,
    27512,
    27513,
    27514
  ],
  "images": [],
  "casualties": null,
  "coordinates": {
    "lat": -3.082,
    "lng": 140.344
  },
  "status": "resolved",
  "magnitude": 6,
  "depth": 35
}