{
  "id": 28035,
  "title": "M6.5 지진 - The 1922 Parkfield, California Earthquake",
  "category": "disaster",
  "era": "contemporary",
  "date": "1922-03-10",
  "location": "The 1922 Parkfield, California Earthquake",
  "summary": "1922-03-10에 The 1922 Parkfield, California Earthquake에서 발생한 규모 6.5의 강진 (Strong). ",
  "description": "## 지진 정보\n\n**규모**: M6.5 (강진 (Strong))\n**발생 시각**: 1922-03-10 11:21:20 UTC\n**위치**: The 1922 Parkfield, California Earthquake\n**깊이**: 0.0 km\n**좌표**: 35.7500°N, -120.2500°E\n\n",
  "timeline": [],
  "theories": [],
  "tags": [
    "자연재해",
    "지진",
    "재난"
  ],
  "sources": [
    {
      "name": "USGS",
      "url": "https://earthquake.usgs.gov/earthquakes/eventpage/ushis675"
    }
  ],
  "relatedIncidents": [
    27937,
    27938,
    27940,
    27941,
    27942
  ],
  "images": [],
  "casualties": null,
  "coordinates": {
    "lat": 35.75,
    "lng": -120.25
  },
  "status": "resolved",
  "magnitude": 6.5,
  "depth": 0
}