{
  "id": 31053,
  "title": "1787년 SAN MARCOS 쓰나미",
  "category": "disaster",
  "era": "modern",
  "date": "1787-04-03",
  "location": "SAN MARCOS, MEXICO",
  "summary": "1787년 SAN MARCOS, MEXICO에서 발생한 쓰나미. 원인: 지진 (Earthquake). 최대 파고: 4.0m. ",
  "description": "## 쓰나미 정보\n\n**발생 일시**: 1787-04-03 15:30 UTC\n**위치**: SAN MARCOS, MEXICO\n**원인**: 지진 (Earthquake)\n**이벤트 유효성**: 분석 필요\n\n## 파도 정보\n\n**최대 파고**: 4.0m (중간 (2-5m))\n**측정 지점 수**: 3개\n",
  "timeline": [],
  "theories": [],
  "tags": [
    "쓰나미",
    "자연재해",
    "재난",
    "지진",
    "원양쓰나미"
  ],
  "sources": [
    {
      "name": "NOAA NGDC",
      "url": "https://www.ngdc.noaa.gov/hazel/view/hazards/tsunami/event-more-info/545"
    }
  ],
  "relatedIncidents": [
    31052,
    31054,
    31055,
    31049,
    31050
  ],
  "images": [],
  "casualties": null,
  "coordinates": {
    "lat": 15.5,
    "lng": -97
  },
  "status": "resolved",
  "maxWaveHeight": 4
}