{
  "id": 330,
  "title": "M6.4 지진 - 56 km S of Panguna, Papua New Guinea",
  "category": "disaster",
  "era": "contemporary",
  "date": "2024-09-01",
  "location": "56 km S of Panguna, Papua New Guinea",
  "summary": "2024-09-01에 56 km S of Panguna, Papua New Guinea에서 발생한 규모 6.4의 강진 (Strong). 쓰나미 경보가 발령되었습니다. 2명이 지진을 체감했습니다.",
  "description": "## 지진 정보\n\n**규모**: M6.4 (강진 (Strong))\n**발생 시각**: 2024-09-01 20:13:34 UTC\n**위치**: 56 km S of Panguna, Papua New Guinea\n**깊이**: 39.0 km\n**좌표**: -6.8295°N, 155.5297°E\n\n## 경보 수준\n\n**PAGER 경보**: 녹색(경미)\n\n## 쓰나미\n\n이 지진으로 인해 쓰나미 경보가 발령되었습니다.\n\n## 체감 보고\n\n총 2건의 체감 보고가 접수되었습니다.\n",
  "timeline": [],
  "theories": [],
  "tags": [
    "자연재해",
    "지진",
    "쓰나미",
    "재난"
  ],
  "sources": [
    {
      "name": "USGS",
      "url": "https://earthquake.usgs.gov/earthquakes/eventpage/us6000np3z"
    }
  ],
  "relatedIncidents": [
    254,
    256,
    257,
    261,
    262
  ],
  "images": [],
  "casualties": null,
  "coordinates": {
    "lat": -6.8295,
    "lng": 155.5297
  },
  "status": "resolved",
  "magnitude": 6.4,
  "depth": 39
}