{
  "id": 3475,
  "title": "HIDDEN PINES FIRE  ",
  "category": "disaster",
  "era": "contemporary",
  "date": "2015-10-13",
  "location": "Bastrop (County), Texas, USA",
  "summary": "2016년 Texas에서 발생한 Fire 재난. FEMA 재난 번호: 5116. 재난 선언일: 2015-10-14.",
  "description": "## 개요\n\nHIDDEN PINES FIRE  \n\n**재난 유형**: Fire\n**위치**: Bastrop (County), Texas, USA\n**재난 시작일**: 2015-10-13\n**재난 종료일**: 2015-10-28\n\n## FEMA 정보\n\n- 재난 번호: 5116\n- 선언 유형: FM\n- FEMA 선언 문자열: FM-5116-TX\n",
  "timeline": [],
  "theories": [],
  "tags": [
    "미국",
    "화재",
    "재난"
  ],
  "sources": [
    {
      "name": "OpenFEMA",
      "url": "https://www.fema.gov/disaster/5116"
    }
  ],
  "relatedIncidents": [
    3447,
    3476,
    3515,
    3516,
    3518
  ],
  "images": [],
  "casualties": null,
  "coordinates": null,
  "status": "resolved",
  "femaDisasterNumber": 5116
}