{
  "id": 8383,
  "title": "M6.1 지진 - 47 km NNW of Lae, Papua New Guinea",
  "category": "disaster",
  "era": "contemporary",
  "date": "2005-06-04",
  "location": "47 km NNW of Lae, Papua New Guinea",
  "summary": "2005-06-04에 47 km NNW of Lae, Papua New Guinea에서 발생한 규모 6.1의 강진 (Strong). ",
  "description": "## 지진 정보\n\n**규모**: M6.1 (강진 (Strong))\n**발생 시각**: 2005-06-04 14:50:46 UTC\n**위치**: 47 km NNW of Lae, Papua New Guinea\n**깊이**: 26.0 km\n**좌표**: -6.3190°N, 146.8460°E\n\n",
  "timeline": [],
  "theories": [],
  "tags": [
    "자연재해",
    "지진",
    "재난"
  ],
  "sources": [
    {
      "name": "USGS",
      "url": "https://earthquake.usgs.gov/earthquakes/eventpage/usp000ds6y"
    }
  ],
  "relatedIncidents": [
    8072,
    8083,
    8084,
    8087,
    8088
  ],
  "images": [],
  "casualties": null,
  "coordinates": {
    "lat": -6.319,
    "lng": 146.846
  },
  "status": "resolved",
  "magnitude": 6.1,
  "depth": 26
}