{
  "id": 9231,
  "title": "TORNADOES, FLOODING, SEVERE STORMS, AND HIGH WINDS",
  "category": "disaster",
  "era": "contemporary",
  "date": "2003-07-21",
  "location": "Trumbull (County), Ohio, USA",
  "summary": "2003년 Ohio에서 발생한 Tornado 재난. FEMA 재난 번호: 1484. 재난 선언일: 2003-08-01.",
  "description": "## 개요\n\nTORNADOES, FLOODING, SEVERE STORMS, AND HIGH WINDS\n\n**재난 유형**: Tornado\n**위치**: Trumbull (County), Ohio, USA\n**재난 시작일**: 2003-07-21\n**재난 종료일**: 2003-08-25\n\n## FEMA 정보\n\n- 재난 번호: 1484\n- 선언 유형: DR\n- FEMA 선언 문자열: DR-1484-OH\n",
  "timeline": [],
  "theories": [],
  "tags": [
    "미국",
    "대형재난",
    "토네이도",
    "재난"
  ],
  "sources": [
    {
      "name": "OpenFEMA",
      "url": "https://www.fema.gov/disaster/1484"
    }
  ],
  "relatedIncidents": [
    9032,
    9041,
    9053,
    9073,
    9079
  ],
  "images": [],
  "casualties": null,
  "coordinates": null,
  "status": "resolved",
  "femaDisasterNumber": 1484
}